{"date":{"year":2023,"month":11,"day":3},"items":[{"id":0,"typeName":"Vàng SJC 1L, 10L, 1KG","branch":"Hồ Chí Minh","buy":{"pricePerGram":1864000.0,"currency":"vnd"},"sell":{"pricePerGram":1882666.6666666667,"currency":"vnd"},"updatedAt":"2023-11-03T08:29:44.953"},{"id":0,"typeName":"Vàng SJC 1L, 10L, 1KG","branch":"Hồ Chí Minh","buy":{"pricePerGram":1861333.3333333333,"currency":"vnd"},"sell":{"pricePerGram":1880000.0,"currency":"vnd"},"updatedAt":"2023-11-03T09:04:21.710"},{"id":0,"typeName":"Vàng SJC 1L, 10L, 1KG","branch":"Hồ Chí Minh","buy":{"pricePerGram":1860000.0,"currency":"vnd"},"sell":{"pricePerGram":1878666.6666666667,"currency":"vnd"},"updatedAt":"2023-11-03T09:34:54.173"},{"id":0,"typeName":"Vàng SJC 1L, 10L, 1KG","branch":"Hồ Chí Minh","buy":{"pricePerGram":1858666.6666666667,"currency":"vnd"},"sell":{"pricePerGram":1877333.3333333333,"currency":"vnd"},"updatedAt":"2023-11-03T10:02:37.087"},{"id":0,"typeName":"Vàng SJC 1L, 10L, 1KG","branch":"Hồ Chí Minh","buy":{"pricePerGram":1857333.3333333333,"currency":"vnd"},"sell":{"pricePerGram":1876000.0,"currency":"vnd"},"updatedAt":"2023-11-03T10:28:25.383"},{"id":0,"typeName":"Vàng SJC 1L, 10L, 1KG","branch":"Hồ Chí Minh","buy":{"pricePerGram":1858666.6666666667,"currency":"vnd"},"sell":{"pricePerGram":1877333.3333333333,"currency":"vnd"},"updatedAt":"2023-11-03T10:50:04.680"},{"id":0,"typeName":"Vàng SJC 1L, 10L, 1KG","branch":"Hồ Chí Minh","buy":{"pricePerGram":1857333.3333333333,"currency":"vnd"},"sell":{"pricePerGram":1876000.0,"currency":"vnd"},"updatedAt":"2023-11-03T15:40:26.303"}],"branch":"Hồ Chí Minh"}