{"date":{"year":2019,"month":9,"day":18},"items":[{"id":0,"typeName":"Vàng SJC 1L, 10L, 1KG","branch":"Hồ Chí Minh","buy":{"pricePerGram":1109333.3333333333,"currency":"vnd"},"sell":{"pricePerGram":1117333.3333333333,"currency":"vnd"},"updatedAt":"2019-09-18T01:32:29.000"},{"id":0,"typeName":"Vàng SJC 1L, 10L, 1KG","branch":"Hồ Chí Minh","buy":{"pricePerGram":1110666.6666666667,"currency":"vnd"},"sell":{"pricePerGram":1118666.6666666667,"currency":"vnd"},"updatedAt":"2019-09-18T02:11:01.000"}],"branch":"Hồ Chí Minh"}