{"date":{"year":2021,"month":3,"day":10},"open":{"buy":{"pricePerGram":1458666.6666666667,"currency":"vnd"},"sell":{"pricePerGram":1470666.6666666667,"currency":"vnd"}},"close":{"buy":{"pricePerGram":1466133.3333333333,"currency":"vnd"},"sell":{"pricePerGram":1476800.0,"currency":"vnd"}},"details":[{"price":{"buy":{"pricePerGram":1466666.6666666667,"currency":"vnd"},"sell":{"pricePerGram":1477333.3333333333,"currency":"vnd"}},"updatedAt":"2021-03-10T01:26:54.000"},{"price":{"buy":{"pricePerGram":1465333.3333333333,"currency":"vnd"},"sell":{"pricePerGram":1476000.0,"currency":"vnd"}},"updatedAt":"2021-03-10T01:38:23.000"},{"price":{"buy":{"pricePerGram":1466666.6666666667,"currency":"vnd"},"sell":{"pricePerGram":1477333.3333333333,"currency":"vnd"}},"updatedAt":"2021-03-10T01:39:32.000"},{"price":{"buy":{"pricePerGram":1465333.3333333333,"currency":"vnd"},"sell":{"pricePerGram":1476000.0,"currency":"vnd"}},"updatedAt":"2021-03-10T01:42:35.000"},{"price":{"buy":{"pricePerGram":1464000.0,"currency":"vnd"},"sell":{"pricePerGram":1474666.6666666667,"currency":"vnd"}},"updatedAt":"2021-03-10T02:32:21.000"},{"price":{"buy":{"pricePerGram":1465333.3333333333,"currency":"vnd"},"sell":{"pricePerGram":1476000.0,"currency":"vnd"}},"updatedAt":"2021-03-10T03:47:26.000"},{"price":{"buy":{"pricePerGram":1466666.6666666667,"currency":"vnd"},"sell":{"pricePerGram":1477333.3333333333,"currency":"vnd"}},"updatedAt":"2021-03-10T08:00:37.000"},{"price":{"buy":{"pricePerGram":1466133.3333333333,"currency":"vnd"},"sell":{"pricePerGram":1476800.0,"currency":"vnd"}},"updatedAt":"2021-03-10T08:21:21.000"}]}