{"date":{"year":2021,"month":11,"day":11},"open":{"buy":{"pricePerGram":1565333.3333333333,"currency":"vnd"},"sell":{"pricePerGram":1584000.0,"currency":"vnd"}},"close":{"buy":{"pricePerGram":1569333.3333333333,"currency":"vnd"},"sell":{"pricePerGram":1588000.0,"currency":"vnd"}},"details":[{"price":{"buy":{"pricePerGram":1572000.0,"currency":"vnd"},"sell":{"pricePerGram":1590666.6666666667,"currency":"vnd"}},"updatedAt":"2021-11-11T01:28:55.000"},{"price":{"buy":{"pricePerGram":1570666.6666666667,"currency":"vnd"},"sell":{"pricePerGram":1589333.3333333333,"currency":"vnd"}},"updatedAt":"2021-11-11T01:40:31.000"},{"price":{"buy":{"pricePerGram":1569333.3333333333,"currency":"vnd"},"sell":{"pricePerGram":1588000.0,"currency":"vnd"}},"updatedAt":"2021-11-11T02:14:39.000"}]}