{"date":{"year":2023,"month":7,"day":20},"open":{"buy":{"pricePerGram":1776000.0,"currency":"vnd"},"sell":{"pricePerGram":1792000.0,"currency":"vnd"}},"close":{"buy":{"pricePerGram":1776000.0,"currency":"vnd"},"sell":{"pricePerGram":1792000.0,"currency":"vnd"}},"details":[{"price":{"buy":{"pricePerGram":1776000.0,"currency":"vnd"},"sell":{"pricePerGram":1792000.0,"currency":"vnd"}},"updatedAt":"2023-07-20T01:28:01.000"},{"price":{"buy":{"pricePerGram":1777333.3333333333,"currency":"vnd"},"sell":{"pricePerGram":1793333.3333333333,"currency":"vnd"}},"updatedAt":"2023-07-20T01:54:43.000"},{"price":{"buy":{"pricePerGram":1776000.0,"currency":"vnd"},"sell":{"pricePerGram":1792000.0,"currency":"vnd"}},"updatedAt":"2023-07-20T07:49:09.000"}]}