{"date":{"year":2020,"month":10,"day":1},"open":{"buy":{"pricePerGram":1481333.3333333333,"currency":"vnd"},"sell":{"pricePerGram":1494666.6666666667,"currency":"vnd"}},"close":{"buy":{"pricePerGram":1481333.3333333333,"currency":"vnd"},"sell":{"pricePerGram":1494666.6666666667,"currency":"vnd"}},"details":[{"price":{"buy":{"pricePerGram":1469333.3333333333,"currency":"vnd"},"sell":{"pricePerGram":1482666.6666666667,"currency":"vnd"}},"updatedAt":"2020-10-01T00:00:00.000"},{"price":{"buy":{"pricePerGram":1470666.6666666667,"currency":"vnd"},"sell":{"pricePerGram":1484000.0,"currency":"vnd"}},"updatedAt":"2020-10-01T01:33:41.000"},{"price":{"buy":{"pricePerGram":1472000.0,"currency":"vnd"},"sell":{"pricePerGram":1485333.3333333333,"currency":"vnd"}},"updatedAt":"2020-10-01T01:47:39.000"},{"price":{"buy":{"pricePerGram":1473333.3333333333,"currency":"vnd"},"sell":{"pricePerGram":1486666.6666666667,"currency":"vnd"}},"updatedAt":"2020-10-01T02:42:20.000"},{"price":{"buy":{"pricePerGram":1474666.6666666667,"currency":"vnd"},"sell":{"pricePerGram":1488000.0,"currency":"vnd"}},"updatedAt":"2020-10-01T03:06:57.000"},{"price":{"buy":{"pricePerGram":1476000.0,"currency":"vnd"},"sell":{"pricePerGram":1489333.3333333333,"currency":"vnd"}},"updatedAt":"2020-10-01T06:34:08.000"},{"price":{"buy":{"pricePerGram":1477333.3333333333,"currency":"vnd"},"sell":{"pricePerGram":1490666.6666666667,"currency":"vnd"}},"updatedAt":"2020-10-01T06:40:37.000"},{"price":{"buy":{"pricePerGram":1478666.6666666667,"currency":"vnd"},"sell":{"pricePerGram":1492000.0,"currency":"vnd"}},"updatedAt":"2020-10-01T07:13:25.000"},{"price":{"buy":{"pricePerGram":1480000.0,"currency":"vnd"},"sell":{"pricePerGram":1493333.3333333333,"currency":"vnd"}},"updatedAt":"2020-10-01T08:17:08.000"},{"price":{"buy":{"pricePerGram":1481333.3333333333,"currency":"vnd"},"sell":{"pricePerGram":1494666.6666666667,"currency":"vnd"}},"updatedAt":"2020-10-01T09:04:19.000"}]}