{"date":{"year":2016,"month":6,"day":10},"items":[{"id":0,"typeName":"Vàng SJC 1L, 10L, 1KG","branch":"Hồ Chí Minh","buy":{"pricePerGram":896800.0,"currency":"vnd"},"sell":{"pricePerGram":903200.0,"currency":"vnd"},"updatedAt":"2016-06-10T01:08:13.000"},{"id":0,"typeName":"Vàng SJC 1L, 10L, 1KG","branch":"Hồ Chí Minh","buy":{"pricePerGram":897333.3333333334,"currency":"vnd"},"sell":{"pricePerGram":903733.3333333334,"currency":"vnd"},"updatedAt":"2016-06-10T01:51:42.000"},{"id":0,"typeName":"Vàng SJC 1L, 10L, 1KG","branch":"Hồ Chí Minh","buy":{"pricePerGram":897600.0,"currency":"vnd"},"sell":{"pricePerGram":904000.0,"currency":"vnd"},"updatedAt":"2016-06-10T01:59:35.000"},{"id":0,"typeName":"Vàng SJC 1L, 10L, 1KG","branch":"Hồ Chí Minh","buy":{"pricePerGram":898133.3333333334,"currency":"vnd"},"sell":{"pricePerGram":904533.3333333334,"currency":"vnd"},"updatedAt":"2016-06-10T03:39:06.000"},{"id":0,"typeName":"Vàng SJC 1L, 10L, 1KG","branch":"Hồ Chí Minh","buy":{"pricePerGram":898666.6666666666,"currency":"vnd"},"sell":{"pricePerGram":905066.6666666666,"currency":"vnd"},"updatedAt":"2016-06-10T07:11:29.000"},{"id":0,"typeName":"Vàng SJC 1L, 10L, 1KG","branch":"Hồ Chí Minh","buy":{"pricePerGram":898933.3333333334,"currency":"vnd"},"sell":{"pricePerGram":905333.3333333334,"currency":"vnd"},"updatedAt":"2016-06-10T07:18:44.000"},{"id":0,"typeName":"Vàng SJC 1L, 10L, 1KG","branch":"Hồ Chí Minh","buy":{"pricePerGram":898400.0,"currency":"vnd"},"sell":{"pricePerGram":904800.0,"currency":"vnd"},"updatedAt":"2016-06-10T08:44:51.000"}],"branch":"Hồ Chí Minh"}