{"date":{"year":2022,"month":1,"day":6},"open":{"buy":{"pricePerGram":1626666.6666666667,"currency":"vnd"},"sell":{"pricePerGram":1645333.3333333333,"currency":"vnd"}},"close":{"buy":{"pricePerGram":1620000.0,"currency":"vnd"},"sell":{"pricePerGram":1638666.6666666667,"currency":"vnd"}},"details":[{"price":{"buy":{"pricePerGram":1625333.3333333333,"currency":"vnd"},"sell":{"pricePerGram":1644000.0,"currency":"vnd"}},"updatedAt":"2022-01-06T01:31:02.000"},{"price":{"buy":{"pricePerGram":1624000.0,"currency":"vnd"},"sell":{"pricePerGram":1642666.6666666667,"currency":"vnd"}},"updatedAt":"2022-01-06T03:36:08.000"},{"price":{"buy":{"pricePerGram":1622666.6666666667,"currency":"vnd"},"sell":{"pricePerGram":1641333.3333333333,"currency":"vnd"}},"updatedAt":"2022-01-06T04:09:37.000"},{"price":{"buy":{"pricePerGram":1621333.3333333333,"currency":"vnd"},"sell":{"pricePerGram":1640000.0,"currency":"vnd"}},"updatedAt":"2022-01-06T06:50:03.000"},{"price":{"buy":{"pricePerGram":1620000.0,"currency":"vnd"},"sell":{"pricePerGram":1638666.6666666667,"currency":"vnd"}},"updatedAt":"2022-01-06T08:33:14.000"}]}