{"date":{"year":2019,"month":1,"day":22},"open":{"buy":{"pricePerGram":970933.3333333334,"currency":"vnd"},"sell":{"pricePerGram":975733.3333333334,"currency":"vnd"}},"close":{"buy":{"pricePerGram":970133.3333333334,"currency":"vnd"},"sell":{"pricePerGram":974933.3333333334,"currency":"vnd"}},"details":[{"price":{"buy":{"pricePerGram":970400.0,"currency":"vnd"},"sell":{"pricePerGram":975200.0,"currency":"vnd"}},"updatedAt":"2019-01-22T01:36:20.000"},{"price":{"buy":{"pricePerGram":970133.3333333334,"currency":"vnd"},"sell":{"pricePerGram":974933.3333333334,"currency":"vnd"}},"updatedAt":"2019-01-22T01:51:10.000"}]}