{"date":{"year":2016,"month":4,"day":4},"open":{"buy":{"pricePerGram":880000.0,"currency":"vnd"},"sell":{"pricePerGram":887200.0,"currency":"vnd"}},"close":{"buy":{"pricePerGram":879733.3333333334,"currency":"vnd"},"sell":{"pricePerGram":886400.0,"currency":"vnd"}},"details":[{"price":{"buy":{"pricePerGram":880000.0,"currency":"vnd"},"sell":{"pricePerGram":887200.0,"currency":"vnd"}},"updatedAt":"2016-04-04T01:04:58.000"},{"price":{"buy":{"pricePerGram":880000.0,"currency":"vnd"},"sell":{"pricePerGram":886666.6666666666,"currency":"vnd"}},"updatedAt":"2016-04-04T01:08:39.000"},{"price":{"buy":{"pricePerGram":879733.3333333334,"currency":"vnd"},"sell":{"pricePerGram":886400.0,"currency":"vnd"}},"updatedAt":"2016-04-04T01:28:10.000"},{"price":{"buy":{"pricePerGram":880000.0,"currency":"vnd"},"sell":{"pricePerGram":886666.6666666666,"currency":"vnd"}},"updatedAt":"2016-04-04T02:23:34.000"},{"price":{"buy":{"pricePerGram":879733.3333333334,"currency":"vnd"},"sell":{"pricePerGram":886400.0,"currency":"vnd"}},"updatedAt":"2016-04-04T02:51:35.000"},{"price":{"buy":{"pricePerGram":879466.6666666666,"currency":"vnd"},"sell":{"pricePerGram":886133.3333333334,"currency":"vnd"}},"updatedAt":"2016-04-04T06:46:29.000"},{"price":{"buy":{"pricePerGram":879733.3333333334,"currency":"vnd"},"sell":{"pricePerGram":886400.0,"currency":"vnd"}},"updatedAt":"2016-04-04T07:19:42.000"},{"price":{"buy":{"pricePerGram":880000.0,"currency":"vnd"},"sell":{"pricePerGram":886666.6666666666,"currency":"vnd"}},"updatedAt":"2016-04-04T07:33:13.000"},{"price":{"buy":{"pricePerGram":879733.3333333334,"currency":"vnd"},"sell":{"pricePerGram":886400.0,"currency":"vnd"}},"updatedAt":"2016-04-04T08:38:34.000"}]}