{"date":{"year":2016,"month":6,"day":28},"open":{"buy":{"pricePerGram":929333.3333333334,"currency":"vnd"},"sell":{"pricePerGram":942666.6666666666,"currency":"vnd"}},"close":{"buy":{"pricePerGram":923733.3333333334,"currency":"vnd"},"sell":{"pricePerGram":934400.0,"currency":"vnd"}},"details":[{"price":{"buy":{"pricePerGram":928000.0,"currency":"vnd"},"sell":{"pricePerGram":938666.6666666666,"currency":"vnd"}},"updatedAt":"2016-06-28T01:21:01.000"},{"price":{"buy":{"pricePerGram":929333.3333333334,"currency":"vnd"},"sell":{"pricePerGram":940000.0,"currency":"vnd"}},"updatedAt":"2016-06-28T01:21:32.000"},{"price":{"buy":{"pricePerGram":928800.0,"currency":"vnd"},"sell":{"pricePerGram":939466.6666666666,"currency":"vnd"}},"updatedAt":"2016-06-28T01:39:48.000"},{"price":{"buy":{"pricePerGram":928000.0,"currency":"vnd"},"sell":{"pricePerGram":938666.6666666666,"currency":"vnd"}},"updatedAt":"2016-06-28T01:45:21.000"},{"price":{"buy":{"pricePerGram":928533.3333333334,"currency":"vnd"},"sell":{"pricePerGram":939200.0,"currency":"vnd"}},"updatedAt":"2016-06-28T02:24:22.000"},{"price":{"buy":{"pricePerGram":928000.0,"currency":"vnd"},"sell":{"pricePerGram":938666.6666666666,"currency":"vnd"}},"updatedAt":"2016-06-28T03:04:26.000"},{"price":{"buy":{"pricePerGram":927466.6666666666,"currency":"vnd"},"sell":{"pricePerGram":938133.3333333334,"currency":"vnd"}},"updatedAt":"2016-06-28T03:44:16.000"},{"price":{"buy":{"pricePerGram":926933.3333333334,"currency":"vnd"},"sell":{"pricePerGram":937600.0,"currency":"vnd"}},"updatedAt":"2016-06-28T04:19:34.000"},{"price":{"buy":{"pricePerGram":926133.3333333334,"currency":"vnd"},"sell":{"pricePerGram":936800.0,"currency":"vnd"}},"updatedAt":"2016-06-28T07:19:58.000"},{"price":{"buy":{"pricePerGram":925333.3333333334,"currency":"vnd"},"sell":{"pricePerGram":936000.0,"currency":"vnd"}},"updatedAt":"2016-06-28T07:29:41.000"},{"price":{"buy":{"pricePerGram":924266.6666666666,"currency":"vnd"},"sell":{"pricePerGram":934933.3333333334,"currency":"vnd"}},"updatedAt":"2016-06-28T08:14:21.000"},{"price":{"buy":{"pricePerGram":923733.3333333334,"currency":"vnd"},"sell":{"pricePerGram":934400.0,"currency":"vnd"}},"updatedAt":"2016-06-28T09:05:59.000"}]}