{"date":{"year":2024,"month":2,"day":15},"open":{"buy":{"pricePerGram":2045333.3333333333,"currency":"vnd"},"sell":{"pricePerGram":2104000.0,"currency":"vnd"}},"close":{"buy":{"pricePerGram":2040000.0,"currency":"vnd"},"sell":{"pricePerGram":2101333.3333333335,"currency":"vnd"}},"details":[{"price":{"buy":{"pricePerGram":2010666.6666666667,"currency":"vnd"},"sell":{"pricePerGram":2072000.0,"currency":"vnd"}},"updatedAt":"2024-02-15T08:32:46.647"},{"price":{"buy":{"pricePerGram":2005333.3333333333,"currency":"vnd"},"sell":{"pricePerGram":2066666.6666666667,"currency":"vnd"}},"updatedAt":"2024-02-15T09:55:34.880"},{"price":{"buy":{"pricePerGram":2010666.6666666667,"currency":"vnd"},"sell":{"pricePerGram":2072000.0,"currency":"vnd"}},"updatedAt":"2024-02-15T10:48:09.410"},{"price":{"buy":{"pricePerGram":2018666.6666666667,"currency":"vnd"},"sell":{"pricePerGram":2080000.0,"currency":"vnd"}},"updatedAt":"2024-02-15T13:46:26.487"},{"price":{"buy":{"pricePerGram":2026666.6666666667,"currency":"vnd"},"sell":{"pricePerGram":2088000.0,"currency":"vnd"}},"updatedAt":"2024-02-15T14:30:01.577"},{"price":{"buy":{"pricePerGram":2026666.6666666667,"currency":"vnd"},"sell":{"pricePerGram":2088000.0,"currency":"vnd"}},"updatedAt":"2024-02-15T14:48:01.087"},{"price":{"buy":{"pricePerGram":2026666.6666666667,"currency":"vnd"},"sell":{"pricePerGram":2088000.0,"currency":"vnd"}},"updatedAt":"2024-02-15T14:48:24.923"},{"price":{"buy":{"pricePerGram":2026666.6666666667,"currency":"vnd"},"sell":{"pricePerGram":2088000.0,"currency":"vnd"}},"updatedAt":"2024-02-15T14:48:51.200"},{"price":{"buy":{"pricePerGram":2026666.6666666667,"currency":"vnd"},"sell":{"pricePerGram":2088000.0,"currency":"vnd"}},"updatedAt":"2024-02-15T14:49:09.147"},{"price":{"buy":{"pricePerGram":2032000.0,"currency":"vnd"},"sell":{"pricePerGram":2093333.3333333333,"currency":"vnd"}},"updatedAt":"2024-02-15T15:20:23.450"},{"price":{"buy":{"pricePerGram":2040000.0,"currency":"vnd"},"sell":{"pricePerGram":2101333.3333333335,"currency":"vnd"}},"updatedAt":"2024-02-15T15:56:26.203"}]}