{"date":{"year":2023,"month":11,"day":9},"open":{"buy":{"pricePerGram":1848000.0,"currency":"vnd"},"sell":{"pricePerGram":1874666.6666666667,"currency":"vnd"}},"close":{"buy":{"pricePerGram":1842666.6666666667,"currency":"vnd"},"sell":{"pricePerGram":1869333.3333333333,"currency":"vnd"}},"details":[{"price":{"buy":{"pricePerGram":1842666.6666666667,"currency":"vnd"},"sell":{"pricePerGram":1869333.3333333333,"currency":"vnd"}},"updatedAt":"2023-11-09T08:34:47.427"},{"price":{"buy":{"pricePerGram":1845333.3333333333,"currency":"vnd"},"sell":{"pricePerGram":1872000.0,"currency":"vnd"}},"updatedAt":"2023-11-09T10:06:12.210"},{"price":{"buy":{"pricePerGram":1848000.0,"currency":"vnd"},"sell":{"pricePerGram":1874666.6666666667,"currency":"vnd"}},"updatedAt":"2023-11-09T10:48:50.863"},{"price":{"buy":{"pricePerGram":1845333.3333333333,"currency":"vnd"},"sell":{"pricePerGram":1872000.0,"currency":"vnd"}},"updatedAt":"2023-11-09T14:06:01.120"},{"price":{"buy":{"pricePerGram":1842666.6666666667,"currency":"vnd"},"sell":{"pricePerGram":1869333.3333333333,"currency":"vnd"}},"updatedAt":"2023-11-09T14:44:40.340"}]}