{"date":{"year":2022,"month":10,"day":17},"open":{"buy":{"pricePerGram":1757333.3333333333,"currency":"vnd"},"sell":{"pricePerGram":1784000.0,"currency":"vnd"}},"close":{"buy":{"pricePerGram":1760000.0,"currency":"vnd"},"sell":{"pricePerGram":1786666.6666666667,"currency":"vnd"}},"details":[{"price":{"buy":{"pricePerGram":1760000.0,"currency":"vnd"},"sell":{"pricePerGram":1786666.6666666667,"currency":"vnd"}},"updatedAt":"2022-10-17T01:23:42.000"},{"price":{"buy":{"pricePerGram":1762666.6666666667,"currency":"vnd"},"sell":{"pricePerGram":1789333.3333333333,"currency":"vnd"}},"updatedAt":"2022-10-17T03:31:11.000"},{"price":{"buy":{"pricePerGram":1764000.0,"currency":"vnd"},"sell":{"pricePerGram":1790666.6666666667,"currency":"vnd"}},"updatedAt":"2022-10-17T06:37:56.000"},{"price":{"buy":{"pricePerGram":1762666.6666666667,"currency":"vnd"},"sell":{"pricePerGram":1789333.3333333333,"currency":"vnd"}},"updatedAt":"2022-10-17T08:23:22.000"},{"price":{"buy":{"pricePerGram":1760000.0,"currency":"vnd"},"sell":{"pricePerGram":1786666.6666666667,"currency":"vnd"}},"updatedAt":"2022-10-17T08:40:00.000"}]}