{"date":{"year":2016,"month":5,"day":19},"open":{"buy":{"pricePerGram":904533.3333333334,"currency":"vnd"},"sell":{"pricePerGram":910666.6666666666,"currency":"vnd"}},"close":{"buy":{"pricePerGram":899733.3333333334,"currency":"vnd"},"sell":{"pricePerGram":905866.6666666666,"currency":"vnd"}},"details":[{"price":{"buy":{"pricePerGram":901600.0,"currency":"vnd"},"sell":{"pricePerGram":907733.3333333334,"currency":"vnd"}},"updatedAt":"2016-05-19T01:08:55.000"},{"price":{"buy":{"pricePerGram":900533.3333333334,"currency":"vnd"},"sell":{"pricePerGram":906666.6666666666,"currency":"vnd"}},"updatedAt":"2016-05-19T01:15:26.000"},{"price":{"buy":{"pricePerGram":899733.3333333334,"currency":"vnd"},"sell":{"pricePerGram":905866.6666666666,"currency":"vnd"}},"updatedAt":"2016-05-19T01:30:01.000"},{"price":{"buy":{"pricePerGram":900000.0,"currency":"vnd"},"sell":{"pricePerGram":906133.3333333334,"currency":"vnd"}},"updatedAt":"2016-05-19T02:15:56.000"},{"price":{"buy":{"pricePerGram":900533.3333333334,"currency":"vnd"},"sell":{"pricePerGram":906666.6666666666,"currency":"vnd"}},"updatedAt":"2016-05-19T02:20:26.000"},{"price":{"buy":{"pricePerGram":900000.0,"currency":"vnd"},"sell":{"pricePerGram":906133.3333333334,"currency":"vnd"}},"updatedAt":"2016-05-19T02:34:00.000"},{"price":{"buy":{"pricePerGram":900533.3333333334,"currency":"vnd"},"sell":{"pricePerGram":906666.6666666666,"currency":"vnd"}},"updatedAt":"2016-05-19T02:47:33.000"},{"price":{"buy":{"pricePerGram":900000.0,"currency":"vnd"},"sell":{"pricePerGram":932800.0,"currency":"vnd"}},"updatedAt":"2016-05-19T06:31:22.000"},{"price":{"buy":{"pricePerGram":900000.0,"currency":"vnd"},"sell":{"pricePerGram":906133.3333333334,"currency":"vnd"}},"updatedAt":"2016-05-19T06:34:49.000"},{"price":{"buy":{"pricePerGram":899466.6666666666,"currency":"vnd"},"sell":{"pricePerGram":905600.0,"currency":"vnd"}},"updatedAt":"2016-05-19T06:36:29.000"},{"price":{"buy":{"pricePerGram":899200.0,"currency":"vnd"},"sell":{"pricePerGram":905333.3333333334,"currency":"vnd"}},"updatedAt":"2016-05-19T06:48:42.000"},{"price":{"buy":{"pricePerGram":898933.3333333334,"currency":"vnd"},"sell":{"pricePerGram":905066.6666666666,"currency":"vnd"}},"updatedAt":"2016-05-19T06:50:06.000"},{"price":{"buy":{"pricePerGram":899200.0,"currency":"vnd"},"sell":{"pricePerGram":905333.3333333334,"currency":"vnd"}},"updatedAt":"2016-05-19T07:33:52.000"},{"price":{"buy":{"pricePerGram":899733.3333333334,"currency":"vnd"},"sell":{"pricePerGram":905866.6666666666,"currency":"vnd"}},"updatedAt":"2016-05-19T07:46:55.000"},{"price":{"buy":{"pricePerGram":899466.6666666666,"currency":"vnd"},"sell":{"pricePerGram":905600.0,"currency":"vnd"}},"updatedAt":"2016-05-19T08:29:42.000"},{"price":{"buy":{"pricePerGram":899733.3333333334,"currency":"vnd"},"sell":{"pricePerGram":905866.6666666666,"currency":"vnd"}},"updatedAt":"2016-05-19T09:49:48.000"}]}