{"date":{"year":2018,"month":2,"day":22},"open":{"buy":{"pricePerGram":983200.0,"currency":"vnd"},"sell":{"pricePerGram":989866.6666666666,"currency":"vnd"}},"close":{"buy":{"pricePerGram":983466.6666666666,"currency":"vnd"},"sell":{"pricePerGram":986933.3333333334,"currency":"vnd"}},"details":[{"price":{"buy":{"pricePerGram":982933.3333333334,"currency":"vnd"},"sell":{"pricePerGram":988800.0,"currency":"vnd"}},"updatedAt":"2018-02-22T01:25:48.000"},{"price":{"buy":{"pricePerGram":984000.0,"currency":"vnd"},"sell":{"pricePerGram":988533.3333333334,"currency":"vnd"}},"updatedAt":"2018-02-22T01:37:09.000"},{"price":{"buy":{"pricePerGram":984533.3333333334,"currency":"vnd"},"sell":{"pricePerGram":988533.3333333334,"currency":"vnd"}},"updatedAt":"2018-02-22T01:41:51.000"},{"price":{"buy":{"pricePerGram":984533.3333333334,"currency":"vnd"},"sell":{"pricePerGram":988000.0,"currency":"vnd"}},"updatedAt":"2018-02-22T02:19:36.000"},{"price":{"buy":{"pricePerGram":984000.0,"currency":"vnd"},"sell":{"pricePerGram":987466.6666666666,"currency":"vnd"}},"updatedAt":"2018-02-22T02:46:23.000"},{"price":{"buy":{"pricePerGram":983733.3333333334,"currency":"vnd"},"sell":{"pricePerGram":987200.0,"currency":"vnd"}},"updatedAt":"2018-02-22T06:52:05.000"},{"price":{"buy":{"pricePerGram":983200.0,"currency":"vnd"},"sell":{"pricePerGram":986666.6666666666,"currency":"vnd"}},"updatedAt":"2018-02-22T07:08:57.000"},{"price":{"buy":{"pricePerGram":982933.3333333334,"currency":"vnd"},"sell":{"pricePerGram":986400.0,"currency":"vnd"}},"updatedAt":"2018-02-22T07:12:50.000"},{"price":{"buy":{"pricePerGram":983200.0,"currency":"vnd"},"sell":{"pricePerGram":986666.6666666666,"currency":"vnd"}},"updatedAt":"2018-02-22T07:55:50.000"},{"price":{"buy":{"pricePerGram":983466.6666666666,"currency":"vnd"},"sell":{"pricePerGram":986933.3333333334,"currency":"vnd"}},"updatedAt":"2018-02-22T09:15:43.000"}]}