{"date":{"year":2016,"month":2,"day":17},"items":[{"id":0,"typeName":"Vàng SJC 1L, 10L, 1KG","branch":"Hồ Chí Minh","buy":{"pricePerGram":889333.3333333334,"currency":"vnd"},"sell":{"pricePerGram":900000.0,"currency":"vnd"},"updatedAt":"2016-02-17T00:22:44.000"},{"id":0,"typeName":"Vàng SJC 1L, 10L, 1KG","branch":"Hồ Chí Minh","buy":{"pricePerGram":890666.6666666666,"currency":"vnd"},"sell":{"pricePerGram":901333.3333333334,"currency":"vnd"},"updatedAt":"2016-02-17T01:15:22.000"},{"id":0,"typeName":"Vàng SJC 1L, 10L, 1KG","branch":"Hồ Chí Minh","buy":{"pricePerGram":888000.0,"currency":"vnd"},"sell":{"pricePerGram":900000.0,"currency":"vnd"},"updatedAt":"2016-02-17T02:13:54.000"},{"id":0,"typeName":"Vàng SJC 1L, 10L, 1KG","branch":"Hồ Chí Minh","buy":{"pricePerGram":888000.0,"currency":"vnd"},"sell":{"pricePerGram":900000.0,"currency":"vnd"},"updatedAt":"2016-02-17T02:14:43.000"},{"id":0,"typeName":"Vàng SJC 1L, 10L, 1KG","branch":"Hồ Chí Minh","buy":{"pricePerGram":889333.3333333334,"currency":"vnd"},"sell":{"pricePerGram":901333.3333333334,"currency":"vnd"},"updatedAt":"2016-02-17T03:16:50.000"},{"id":0,"typeName":"Vàng SJC 1L, 10L, 1KG","branch":"Hồ Chí Minh","buy":{"pricePerGram":888000.0,"currency":"vnd"},"sell":{"pricePerGram":900000.0,"currency":"vnd"},"updatedAt":"2016-02-17T06:33:27.000"},{"id":0,"typeName":"Vàng SJC 1L, 10L, 1KG","branch":"Hồ Chí Minh","buy":{"pricePerGram":886666.6666666666,"currency":"vnd"},"sell":{"pricePerGram":898666.6666666666,"currency":"vnd"},"updatedAt":"2016-02-17T08:09:12.000"},{"id":0,"typeName":"Vàng SJC 1L, 10L, 1KG","branch":"Hồ Chí Minh","buy":{"pricePerGram":886666.6666666666,"currency":"vnd"},"sell":{"pricePerGram":898666.6666666666,"currency":"vnd"},"updatedAt":"2016-02-17T08:09:51.000"},{"id":0,"typeName":"Vàng SJC 1L, 10L, 1KG","branch":"Hồ Chí Minh","buy":{"pricePerGram":885333.3333333334,"currency":"vnd"},"sell":{"pricePerGram":897333.3333333334,"currency":"vnd"},"updatedAt":"2016-02-17T08:41:33.000"},{"id":0,"typeName":"Vàng SJC 1L, 10L, 1KG","branch":"Hồ Chí Minh","buy":{"pricePerGram":884000.0,"currency":"vnd"},"sell":{"pricePerGram":896000.0,"currency":"vnd"},"updatedAt":"2016-02-17T09:06:55.000"},{"id":0,"typeName":"Vàng SJC 1L, 10L, 1KG","branch":"Hồ Chí Minh","buy":{"pricePerGram":882666.6666666666,"currency":"vnd"},"sell":{"pricePerGram":894666.6666666666,"currency":"vnd"},"updatedAt":"2016-02-17T09:46:33.000"},{"id":0,"typeName":"Vàng SJC 1L, 10L, 1KG","branch":"Hồ Chí Minh","buy":{"pricePerGram":883466.6666666666,"currency":"vnd"},"sell":{"pricePerGram":895466.6666666666,"currency":"vnd"},"updatedAt":"2016-02-17T09:56:33.000"},{"id":0,"typeName":"Vàng SJC 1L, 10L, 1KG","branch":"Hồ Chí Minh","buy":{"pricePerGram":882666.6666666666,"currency":"vnd"},"sell":{"pricePerGram":894666.6666666666,"currency":"vnd"},"updatedAt":"2016-02-17T11:00:01.000"}],"branch":"Hồ Chí Minh"}